flamapy/core/__init__.py
flamapy/core/config.py
flamapy/core/discover.py
flamapy/core/exceptions.py
flamapy/core/plugins.py
flamapy/core/utils.py
flamapy/core/models/__init__.py
flamapy/core/models/ast.py
flamapy/core/models/variability_model.py
flamapy/core/operations/__init__.py
flamapy/core/operations/abstract_operation.py
flamapy/core/operations/atomic_sets.py
flamapy/core/operations/average_branching_factor.py
flamapy/core/operations/commonality.py
flamapy/core/operations/configurations.py
flamapy/core/operations/configurations_number.py
flamapy/core/operations/core_features.py
flamapy/core/operations/count_leafs.py
flamapy/core/operations/dead_features.py
flamapy/core/operations/error_detection.py
flamapy/core/operations/error_diagnosis.py
flamapy/core/operations/estimated_configurations_number.py
flamapy/core/operations/false_optional_features.py
flamapy/core/operations/filter.py
flamapy/core/operations/metrics_operation.py
flamapy/core/operations/sampling.py
flamapy/core/operations/satisfiable.py
flamapy/core/operations/satisfiable_configuration.py
flamapy/core/operations/variability.py
flamapy/core/transformations/__init__.py
flamapy/core/transformations/abstract_transformation.py
flamapy/core/transformations/model_to_model.py
flamapy/core/transformations/model_to_text.py
flamapy/core/transformations/text_to_model.py
flamapy/metamodels/configuration_metamodel/__init__.py
flamapy/metamodels/configuration_metamodel/models/__init__.py
flamapy/metamodels/configuration_metamodel/models/configuration.py
flamapy/metamodels/configuration_metamodel/transformations/__init__.py
flamapy/metamodels/configuration_metamodel/transformations/configuration_basic_reader.py
flamapy_fw-2.0.1.dist-info/METADATA
flamapy_fw-2.0.1.dist-info/WHEEL
flamapy_fw-2.0.1.dist-info/entry_points.txt
flamapy_fw-2.0.1.dist-info/top_level.txt
flamapy_fw-2.0.1.dist-info/RECORD
