Metadata-Version: 2.1
Name: flamapy-fw
Version: 2.0.1
Summary: Flamapy is a Python-based AAFM framework that takes into consideration previous AAFM tool designs and enables multi-solver and multi-metamodel support for the integration of AAFM tooling on the Python ecosystem.
Home-page: https://github.com/flamapy/core
Author: Flamapy
Author-email: flamapy@us.es
License: UNKNOWN
Platform: UNKNOWN
Classifier: Programming Language :: Python :: 3
Classifier: License :: OSI Approved :: GNU General Public License v3 or later (GPLv3+)
Classifier: Operating System :: OS Independent
Requires-Python: >=3.9
Provides-Extra: dev
